quda/factor/__init__.py
quda/factor/completer.py
quda/factor/consts.py
quda/factor/core.py
quda/factor/errors.py
quda/factor/evaluator.py
quda/factor/resolver.py
quda/factor/utils.py
quda_alpha-0.1.1.dist-info/METADATA
quda_alpha-0.1.1.dist-info/WHEEL
quda_alpha-0.1.1.dist-info/top_level.txt
quda_alpha-0.1.1.dist-info/RECORD
