Metadata-Version: 2.4
Name: quda-alpha
Version: 0.1.1
License-Expression: MIT
Requires-Python: >=3.12
Requires-Dist: pandas>=2.3.0
Requires-Dist: polars>=1.30.0
Requires-Dist: quda-core>=1.0.3
Requires-Dist: varname>=0.14.0
Requires-Dist: xcals>=0.0.4
Requires-Dist: ygo>=1.1.4
